bobtemplates.plone-7.0.0-py3.11-nspkg.pth
bobtemplates/plone/__init__.py
bobtemplates/plone/addon.py
bobtemplates/plone/base.py
bobtemplates/plone/behavior.py
bobtemplates/plone/bobregistry.py
bobtemplates/plone/buildout.py
bobtemplates/plone/content_type.py
bobtemplates/plone/controlpanel.py
bobtemplates/plone/form.py
bobtemplates/plone/indexer.py
bobtemplates/plone/mockup_pattern.py
bobtemplates/plone/portlet.py
bobtemplates/plone/restapi_service.py
bobtemplates/plone/site_initialization.py
bobtemplates/plone/subscriber.py
bobtemplates/plone/svelte_app.py
bobtemplates/plone/theme.py
bobtemplates/plone/theme_barceloneta.py
bobtemplates/plone/theme_basic.py
bobtemplates/plone/upgrade_step.py
bobtemplates/plone/utils.py
bobtemplates/plone/view.py
bobtemplates/plone/viewlet.py
bobtemplates/plone/vocabulary.py
bobtemplates/plone/addon/.mrbob.ini
bobtemplates/plone/behavior/.mrbob.ini
bobtemplates/plone/behavior/behaviors/+behavior_name_normalized+.py.bob
bobtemplates/plone/behavior/behaviors/__init__.py
bobtemplates/plone/behavior/behaviors/configure.zcml.example.bob
bobtemplates/plone/behavior/tests/test_behavior_+behavior_name_normalized+.py.bob
bobtemplates/plone/buildout/.gitignore
bobtemplates/plone/buildout/.mrbob.ini
bobtemplates/plone/buildout/base.cfg.bob
bobtemplates/plone/buildout/bobtemplate.cfg.bob
bobtemplates/plone/buildout/buildout.cfg.bob
bobtemplates/plone/buildout/constraints.txt.bob
bobtemplates/plone/buildout/requirements.txt
bobtemplates/plone/content_type/.mrbob.ini
bobtemplates/plone/content_type/content/+dexterity_type_name_normalized+.py.bob
bobtemplates/plone/content_type/content/+dexterity_type_name_normalized+.xml.bob
bobtemplates/plone/content_type/content/__init__.py
bobtemplates/plone/content_type/profiles/default/types.xml.example.bob
bobtemplates/plone/content_type/profiles/default/registry/plone.displayed_types.+dexterity_type_fti_file_name+.xml.bob
bobtemplates_plone-7.0.0.dist-info/licenses/LICENSE.GPL
bobtemplates_plone-7.0.0.dist-info/licenses/LICENSE.rst
bobtemplates_plone-7.0.0.dist-info/METADATA
bobtemplates_plone-7.0.0.dist-info/WHEEL
bobtemplates_plone-7.0.0.dist-info/entry_points.txt
bobtemplates_plone-7.0.0.dist-info/namespace_packages.txt
bobtemplates_plone-7.0.0.dist-info/top_level.txt
bobtemplates_plone-7.0.0.dist-info/RECORD
