Metadata-Version: 2.4
Name: bobtemplates.plone
Version: 7.0.0
Summary: Templates for Plone projects.
Home-page: https://github.com/plone/bobtemplates.plone/
Author: Plone Foundation
Author-email: plone-developers@lists.sourceforge.net
License: GPL version 2
Project-URL: PyPI, https://pypi.python.org/pypi/bobtemplates.plone
Project-URL: Documentation, https://bobtemplatesplone.readthedocs.io/en/latest/
Project-URL: Source, https://github.com/plone/bobtemplates.plone/
Project-URL: Tracker, https://github.com/plone/bobtemplates.plone/issues
Keywords: web plone zope skeleton project
Classifier: Environment :: Console
Classifier: Framework :: Plone
Classifier: Intended Audience :: Developers
Classifier: Natural Language :: English
Classifier: Operating System :: OS Independent
Classifier: Programming Language :: Python
Classifier: Programming Language :: Python :: 3.11
Classifier: Programming Language :: Python :: 3.12
Classifier: Programming Language :: Python :: 3.13
Classifier: Programming Language :: Python :: 3.14
Classifier: Programming Language :: Python :: Implementation :: CPython
Classifier: Development Status :: 5 - Production/Stable
Classifier: Framework :: Plone
Classifier: Framework :: Plone :: 6.0
Classifier: Framework :: Plone :: 6.1
Classifier: Topic :: Software Development :: Code Generators
Classifier: Topic :: Utilities
Classifier: License :: OSI Approved :: GNU General Public License v2 (GPLv2)
Requires-Python: >=3.11
License-File: LICENSE.GPL
License-File: LICENSE.rst
Requires-Dist: setuptools
Requires-Dist: mr.bob
Requires-Dist: lxml
Requires-Dist: case-conversion<3.0.0
Requires-Dist: colorama
Requires-Dist: tox
Requires-Dist: isort
Requires-Dist: black
Dynamic: author
Dynamic: author-email
Dynamic: classifier
Dynamic: description
Dynamic: home-page
Dynamic: keywords
Dynamic: license
Dynamic: license-file
Dynamic: project-url
Dynamic: requires-dist
Dynamic: requires-python
Dynamic: summary
